pymemos/__init__.py
pymemos-0.2.0.dist-info/METADATA
pymemos-0.2.0.dist-info/WHEEL
pymemos-0.2.0.dist-info/entry_points.txt
pymemos-0.2.0.dist-info/licenses/LICENSE
pymemos-0.2.0.dist-info/RECORD
