Metadata-Version: 2.3
Name: pymemos
Version: 0.2.0
Summary: A Python-based command-line interface for interacting with the Memos API
Project-URL: Homepage, https://github.com/rfzee/pymemos
Project-URL: Bug Tracker, https://github.com/rfzee/pymemos/issues
Author-email: rfzee <rfzee@proton.me>
License: MIT
License-File: LICENSE
Classifier: License :: OSI Approved :: MIT License
Classifier: Operating System :: OS Independent
Classifier: Programming Language :: Python :: 3
Requires-Python: >=3.12
Requires-Dist: click>=8.1.7
Requires-Dist: loguru>=0.7.2
Requires-Dist: requests>=2.32.3
Requires-Dist: tabulate>=0.9.0
